ufa/__init__.py
ufa/_version.py
ufa/client.py
ufa-0.1.2.dist-info/METADATA
ufa-0.1.2.dist-info/WHEEL
ufa-0.1.2.dist-info/RECORD
