Metadata-Version: 2.4
Name: ufa
Version: 0.1.2
Summary: A tiny UFA client
Author-email: Srinivas Gorur-Shandilya <code@srinivas.gs>
Requires-Python: >=3.10
Requires-Dist: anyio>=4.11.0
Requires-Dist: beartype>=0.19.0
Requires-Dist: httpx>=0.28.1
Requires-Dist: nest-asyncio>=1.6.0
Requires-Dist: xxhash>=3.5.0
